katalyst/__init__.py
katalyst/app/__init__.py
katalyst/app/config.py
katalyst/app/execution_controller.py
katalyst/app/main.py
katalyst/app/playbook_navigator.py
katalyst/app/cli/__init__.py
katalyst/app/cli/commands.py
katalyst/app/onboarding/__init__.py
katalyst/app/onboarding/welcome_screens.py
katalyst/app/ui/__init__.py
katalyst/app/ui/input_handler.py
katalyst/coding_agent/__init__.py
katalyst/coding_agent/graph.py
katalyst/coding_agent/nodes/advance_pointer.py
katalyst/coding_agent/nodes/executor.py
katalyst/coding_agent/nodes/human_plan_verification.py
katalyst/coding_agent/nodes/planner.py
katalyst/coding_agent/nodes/replanner.py
katalyst/coding_agent/nodes/summarizer.py
katalyst/coding_agent/prompts/tools/__init__.py
katalyst/coding_agent/prompts/tools/attempt_completion.py
katalyst/coding_agent/prompts/tools/bash.py
katalyst/coding_agent/prompts/tools/create_subtask.py
katalyst/coding_agent/prompts/tools/edit.py
katalyst/coding_agent/prompts/tools/execute_data_code.py
katalyst/coding_agent/prompts/tools/glob.py
katalyst/coding_agent/prompts/tools/grep.py
katalyst/coding_agent/prompts/tools/list_code_definitions.py
katalyst/coding_agent/prompts/tools/ls.py
katalyst/coding_agent/prompts/tools/multiedit.py
katalyst/coding_agent/prompts/tools/read.py
katalyst/coding_agent/prompts/tools/request_user_input.py
katalyst/coding_agent/prompts/tools/write.py
katalyst/coding_agent/tools/attempt_completion.py
katalyst/coding_agent/tools/bash.py
katalyst/coding_agent/tools/create_subtask.py
katalyst/coding_agent/tools/edit.py
katalyst/coding_agent/tools/execute_data_code.py
katalyst/coding_agent/tools/glob.py
katalyst/coding_agent/tools/grep.py
katalyst/coding_agent/tools/list_code_definitions.py
katalyst/coding_agent/tools/ls.py
katalyst/coding_agent/tools/multiedit.py
katalyst/coding_agent/tools/read.py
katalyst/coding_agent/tools/request_user_input.py
katalyst/coding_agent/tools/write.py
katalyst/data_science_agent/__init__.py
katalyst/data_science_agent/graph.py
katalyst-0.9.1.dist-info/licenses/LICENSE
katalyst-0.9.1.dist-info/METADATA
katalyst-0.9.1.dist-info/WHEEL
katalyst-0.9.1.dist-info/entry_points.txt
katalyst-0.9.1.dist-info/top_level.txt
katalyst-0.9.1.dist-info/RECORD
