Metadata-Version: 2.4
Name: katalyst
Version: 0.9.1
Summary: A terminal coding agent for Python.
Author-email: Maruti Agarwal <marutiagarwal@gmail.com>
License-Expression: MIT
Requires-Python: <4.0,>=3.12
License-File: LICENSE
Requires-Dist: openai==1.97.0
Requires-Dist: langgraph==0.5.3
Requires-Dist: langchain-core==0.3.69
Requires-Dist: python-dotenv==1.1.1
Requires-Dist: langchain-openai==0.3.28
Requires-Dist: pathspec==0.12.1
Requires-Dist: tree-sitter==0.21.3
Requires-Dist: tree-sitter-languages==1.10.2
Requires-Dist: rich==14.0.0
Requires-Dist: instructor==1.10.0
Requires-Dist: bm25s==0.2.13
Requires-Dist: thefuzz==0.22.1
Requires-Dist: langchain-ollama==0.3.5
Requires-Dist: langchain-anthropic==0.3.17
Requires-Dist: simple-term-menu==1.6.6
Requires-Dist: langgraph-checkpoint-sqlite==2.0.10
Requires-Dist: langmem==0.0.28
Requires-Dist: langgraph-supervisor<0.0.29,>=0.0.28
Requires-Dist: jupyter-client>=8.6.0
Requires-Dist: ipykernel>=6.29.0
Provides-Extra: test
Requires-Dist: pytest==8.4.0; extra == "test"
Requires-Dist: pytest-cov==6.2.1; extra == "test"
Requires-Dist: pytest-asyncio==1.0.0; extra == "test"
Dynamic: license-file
